{
  "run_metadata": {
    "generated_at": "2026-05-22T06:24:14Z",
    "dry_run": false,
    "analysis_summary_file": "20260522/analysis_results.json",
    "previous_report_source": "20260505/run_report.json"
  },
  "counters": {
    "total": 1,
    "created": 0,
    "simulated": 0,
    "updated_by_comment": 0,
    "closed": 0,
    "skipped": 0,
    "failed": 1
  },
  "records": [
    {
      "repo_url": "https://gitlab.in2p3.fr/gammalearn/gammalearn",
      "platform": "gitlab",
      "pitfalls_count": 0,
      "warnings_count": 2,
      "issue_url": null,
      "analysis_date": "2026-05-22T06:05:07Z",
      "sw_metadata_bot_version": "0.4.3",
      "rsmetacheck_version": "0.3.1",
      "pitfalls_ids": [],
      "warnings_ids": [
        "W001",
        "W004"
      ],
      "action": "failed",
      "reason_code": "publish_exception",
      "findings_signature": "W001|W004",
      "current_commit_id": "924289f57a6437f7753e4b3f19484858aa3c956b",
      "dry_run": true,
      "issue_persistence": "simulated",
      "codemeta_generated": false,
      "codemeta_status": "present",
      "file": "20260522/gitlab_in2p3_fr_gammalearn_gammalearn/pitfall.jsonld",
      "error": "401 Client Error: Unauthorized for url: https://gitlab.in2p3.fr/api/v4/projects/gammalearn%2Fgammalearn/issues",
      "is_transient_error": false,
      "retry_after_seconds": 30,
      "retry_attempt": 1,
      "failed_at": "2026-05-22T06:24:14Z",
      "last_publish_action": "simulated_created"
    }
  ]
}